repo2docs/__init__.py
repo2docs/llm.py
repo2docs/prompts.py
repo2docs/repo2docs.py
repo2docs/repo_to_text.py
repo2docs/text_to_docs.py
repo2docs/utils.py
repo2docs-0.1.24.dist-info/LICENSE
repo2docs-0.1.24.dist-info/METADATA
repo2docs-0.1.24.dist-info/WHEEL
repo2docs-0.1.24.dist-info/entry_points.txt
repo2docs-0.1.24.dist-info/RECORD
