Metadata-Version: 2.1
Name: repo2docs
Version: 0.1.24
Summary: Documentation from your codebase using LLMs
License: MIT
Author: Joe Petrantoni
Author-email: 79169021+jpetrantoni@users.noreply.github.com
Requires-Python: >=3.10,<4.0
Classifier: License :: OSI Approved :: MIT License
Classifier: Programming Language :: Python :: 3
Classifier: Programming Language :: Python :: 3.10
Classifier: Programming Language :: Python :: 3.11
Classifier: Programming Language :: Python :: 3.12
Requires-Dist: anthropic (>=0.25.7,<0.26.0)
Requires-Dist: esprima (>=4.0.1,<5.0.0)
Requires-Dist: inquirerpy (>=0.3.4,<0.4.0)
Requires-Dist: instructor (>=1.2.5,<2.0.0)
Requires-Dist: openai (>=1.25.1,<2.0.0)
Requires-Dist: prompt-toolkit (>=3.0.43,<4.0.0)
Requires-Dist: pycparser (>=2.22,<3.0)
Requires-Dist: python-dotenv (>=1.0.1,<2.0.0)
